openchart/__init__.py
openchart/core.py
openchart/utils.py
openchart-0.2.0.dist-info/licenses/LICENSE
openchart-0.2.0.dist-info/METADATA
openchart-0.2.0.dist-info/WHEEL
openchart-0.2.0.dist-info/top_level.txt
openchart-0.2.0.dist-info/RECORD
